sizif/__init__.py
sizif/ftptasks.py
sizif/keras.py
sizif/storage.py
sizif-0.0.7.dist-info/METADATA
sizif-0.0.7.dist-info/RECORD
sizif-0.0.7.dist-info/WHEEL
sizif-0.0.7.dist-info/top_level.txt
test/__init__.py
test/test_storage.py
