Metadata-Version: 2.1
Name: sizif
Version: 0.0.7
Summary: Deep learning Keras models lifecycle management backup/restore nano framework
Home-page: https://github.com/aristofun/sizif
Author: Michael Butlitsky
Author-email: aristofun@yandex.ru
License: UNKNOWN
Platform: UNKNOWN
Classifier: Development Status :: 2 - Pre-Alpha
Classifier: Intended Audience :: Developers
Classifier: Intended Audience :: Education
Classifier: Intended Audience :: Science/Research
Classifier: Environment :: Console
Classifier: Topic :: Scientific/Engineering :: Artificial Intelligence
Classifier: Topic :: Software Development
Classifier: Topic :: Software Development :: Libraries
Classifier: Topic :: Software Development :: Libraries :: Python Modules
Classifier: Programming Language :: Python :: 3
Classifier: License :: OSI Approved :: MIT License
Classifier: Operating System :: OS Independent
Requires-Dist: numpy (>=1.12)
Requires-Dist: Keras (>=2.2)
